setup.py
p_package.egg-info/PKG-INFO
p_package.egg-info/SOURCES.txt
p_package.egg-info/dependency_links.txt
p_package.egg-info/top_level.txt
packages/__init__.py
packages/encryption.py
packages/generate_random_string.py
packages/getpagination.py
packages/otp.py
packages/uniqueID.py