Metadata-Version: 2.1
Name: p_package
Version: 0.0.1
Summary: unknow
Author: unknow
Classifier: Development Status :: 3 - Alpha
Classifier: Operating System :: OS Independent
Classifier: License :: OSI Approved :: MIT License
Classifier: Programming Language :: Python :: 3
Requires-Python: >=3.6
